airfold_cli/__init__.py
airfold_cli/__main__.py
airfold_cli/_pydantic.py
airfold_cli/api.py
airfold_cli/cli.py
airfold_cli/completion.py
airfold_cli/config.py
airfold_cli/diff.py
airfold_cli/doctor.py
airfold_cli/error.py
airfold_cli/fmt.py
airfold_cli/generate.py
airfold_cli/graph.py
airfold_cli/job.py
airfold_cli/log.py
airfold_cli/models.py
airfold_cli/options.py
airfold_cli/pipe.py
airfold_cli/prompts.py
airfold_cli/pull.py
airfold_cli/push.py
airfold_cli/py.typed
airfold_cli/root.py
airfold_cli/source.py
airfold_cli/ui.py
airfold_cli/utils.py
airfold_cli/version.py
airfold_cli/events/__init__.py
airfold_cli/events/http_log.py
airfold_cli/tui/__init__.py
airfold_cli/tui/diff.py
airfold_cli/tui/progress.py
airfold_cli/tui/renderables.py
airfold_cli/tui/syntax.py
airfold_cli/tui/theme.py
airfold_cli/tui/underline_bar.py
airfold_cli-0.14.3.dist-info/METADATA
airfold_cli-0.14.3.dist-info/WHEEL
airfold_cli-0.14.3.dist-info/entry_points.txt
airfold_cli-0.14.3.dist-info/top_level.txt
airfold_cli-0.14.3.dist-info/RECORD
