Metadata-Version: 2.4
Name: airfold-cli
Version: 0.14.3
Summary: Airfold CLI
Author-email: Constantine Peresypkin <pconstantine@gmail.com>, Oleksandr Bazna <oleksandr.bazna@gmail.com>
Classifier: Development Status :: 3 - Alpha
Classifier: Programming Language :: Python :: 3.10
Classifier: Programming Language :: Python :: 3.11
Classifier: License :: OSI Approved :: Apache Software License
Classifier: Operating System :: OS Independent
Requires-Python: <4,>=3.10
Requires-Dist: boto3
Requires-Dist: pydantic<3.0,>=1.10.4
Requires-Dist: pyyaml!=5.4.0,!=5.4.1,!=6.0.0
Requires-Dist: requests
Requires-Dist: typer>=0.12.5
Requires-Dist: rich
Requires-Dist: merge-args
Requires-Dist: readchar
Requires-Dist: unidiff
Requires-Dist: deepdiff
Requires-Dist: airfold-common<1.0,>=0.13.2
Requires-Dist: tenacity
Requires-Dist: faker
Requires-Dist: cachetools
Requires-Dist: duckdb>=0.10.0
Requires-Dist: pyarrow
Requires-Dist: shortuuid
Requires-Dist: humanize
Requires-Dist: multidict
Provides-Extra: test
Requires-Dist: build; extra == "test"
Requires-Dist: isort; extra == "test"
Requires-Dist: black~=23.3; extra == "test"
Requires-Dist: mypy; extra == "test"
Requires-Dist: pytest; extra == "test"
Requires-Dist: pytest-env; extra == "test"
Requires-Dist: pytest-dotenv; extra == "test"
Requires-Dist: retry; extra == "test"
Requires-Dist: types-pyyaml; extra == "test"
Requires-Dist: types-retry; extra == "test"
Requires-Dist: types-requests; extra == "test"
Requires-Dist: types-cachetools; extra == "test"
Requires-Dist: pytest-order; extra == "test"
Requires-Dist: pytest-xvfb; extra == "test"
Requires-Dist: pytest-timeout; extra == "test"
